MANIFEST.in
lunch_demo.xml
lunch_report.xml
lunch_view.xml
setup.py
./__init__.py
./__openerp__.py
./lunch.py
./report/__init__.py
./report/order.py
./report/report_lunch_order.py
./tests/__init__.py
./tests/test_lunch.py
./wizard/__init__.py
./wizard/lunch_cancel.py
./wizard/lunch_order.py
./wizard/lunch_validation.py
i18n/ar.po
i18n/bg.po
i18n/ca.po
i18n/cs.po
i18n/da.po
i18n/de.po
i18n/es.po
i18n/es_CR.po
i18n/es_MX.po
i18n/es_PY.po
i18n/es_VE.po
i18n/fi.po
i18n/fr.po
i18n/gl.po
i18n/hr.po
i18n/hu.po
i18n/it.po
i18n/ja.po
i18n/ko.po
i18n/lunch.pot
i18n/mk.po
i18n/mn.po
i18n/nl.po
i18n/pt.po
i18n/pt_BR.po
i18n/ro.po
i18n/ru.po
i18n/sl.po
i18n/sr@latin.po
i18n/sv.po
i18n/tr.po
i18n/zh_CN.po
i18n/zh_TW.po
images/alert.jpeg
images/lunch_account.jpeg
images/new_order.jpeg
images/order_by_supplier_analysis.jpeg
openerp_lunch.egg-info/PKG-INFO
openerp_lunch.egg-info/SOURCES.txt
openerp_lunch.egg-info/dependency_links.txt
openerp_lunch.egg-info/requires.txt
openerp_lunch.egg-info/top_level.txt
report/order.rml
report/order.sxw
report/report_lunch_order_view.xml
security/ir.model.access.csv
security/lunch_security.xml
static/src/img/icon.png
wizard/lunch_cancel_view.xml
wizard/lunch_order_view.xml
wizard/lunch_validation_view.xml